s_tasks_api/__init__.py
s_tasks_api/admin.py
s_tasks_api/apps.py
s_tasks_api/filters.py
s_tasks_api/models.py
s_tasks_api/serializers.py
s_tasks_api/settings.py
s_tasks_api/urls.py
s_tasks_api/views.py
s_tasks_api/fixtures/__init__.py
s_tasks_api/migrations/0001_initial.py
s_tasks_api/migrations/0002_grouptask.py
s_tasks_api/migrations/__init__.py
s_tasks_api/permissions/__init__.py
s_tasks_api/permissions/common.py
s_tasks_api/permissions/task_tags.py
s_tasks_api/permissions/tasks.py
s_tasks_api/services/__init__.py
s_tasks_api/services/task_status.py
s_tasks_api/services/tasks.py
s_tasks_api/services/utils.py
s_tasks_api/tests/__init__.py
s_tasks_api/tests/test_task_status.py
s_tasks_api/tests/test_task_tag.py
s_tasks_api/tests/utils.py
s_tasks_api/tests/tasks/__init__.py
s_tasks_api/tests/tasks/test_add.py
s_tasks_api/tests/tasks/test_change.py
s_tasks_api/tests/tasks/test_delete.py
s_tasks_api/tests/tasks/test_read.py
s_tasks_api/tests/tasks/utils.py
django_s_tasks_api-1.0.0.dist-info/LICENSE
django_s_tasks_api-1.0.0.dist-info/METADATA
django_s_tasks_api-1.0.0.dist-info/WHEEL
django_s_tasks_api-1.0.0.dist-info/top_level.txt
django_s_tasks_api-1.0.0.dist-info/RECORD
